dbpoint/__init__.py
dbpoint/datacapsule.py
dbpoint/datacolumn.py
dbpoint/dataset.py
dbpoint/fileops.py
dbpoint/hub.py
dbpoint/lost_and_fount.py
dbpoint/moduleops.py
dbpoint/old_profile_sql.py
dbpoint/perks.py
dbpoint/textops.py
dbpoint/typehelper.py
dbpoint/drivers/__init__.py
dbpoint/drivers/asa.py
dbpoint/drivers/drivers.yaml
dbpoint/drivers/maria.py
dbpoint/drivers/mssql.py
dbpoint/drivers/odbc.py
dbpoint/drivers/oracle.py
dbpoint/drivers/pg.py
dbpoint-0.3.7.dist-info/METADATA
dbpoint-0.3.7.dist-info/WHEEL
dbpoint-0.3.7.dist-info/licenses/LICENSE.txt
dbpoint-0.3.7.dist-info/RECORD
