Metadata-Version: 2.4
Name: dbpoint
Version: 0.3.7
Summary: Single access point for multiple SQL-databases. Purpose to stream data from one to other.
Author: Nauri Nastik
License-File: LICENSE.txt
Classifier: License :: OSI Approved :: MIT License
Classifier: Operating System :: OS Independent
Classifier: Programming Language :: Python :: 3
Requires-Python: >=3.10
Requires-Dist: jinja2
Requires-Dist: loguru
Requires-Dist: pyyaml
